{"source":"var meteor = createSprite(random(50, 350), -20);\nmeteor.setAnimation(\"meteor.jpg_1\");\nvar enemy = createSprite(random(50, 350), -20);\nenemy.setAnimation(\"enemyBlack1_1\");\nenemy.velocityY = 7;\nvar ship = createSprite(200, 350);\nship.setAnimation(\"playerShip1_blue_1\");\nship.scale = 0.75;\nvar bullet = createSprite(ship.x, ship.y - 20, 5, 10);\nbullet.setAnimation(\"bullet 2.0.png_1\");\nbullet.scale = 0.05;\nbullet.visible = 0;\nvar gameState = \"play\";\nvar score = 0;\nvar health = 5;\nfunction updateBackground() {\n  background(\"black\");\n  if (score >= 20) {\n    background(\"red\");\n  }\n  if (health == 3) {\n    background(\"blue\");\n  }\n}\nfunction handleInput() {\n  if (keyDown(\"left\")) {\n    ship.x = ship.x - 10;\n  }\n  if (keyDown(\"right\")) {\n    ship.x = ship.x + 10;\n  }\n  if (keyWentDown(\"space\")) {\n    bullet.velocityY = -10;\n    bullet.scale = 0.1;\n  }\n}\nfunction spawnObstacles() {\n  if (World.frameCount % 60 === 0) {\n    enemy.velocityY = 3;\n  }\n  if (World.frameCount % 90 === 0) {\n    meteor.velocityY = 3;\n  }\n}\nfunction handleCollisions() {\n  if (score >= 150) { gameState = \"win\"; }\n}\nfunction displayUI() {\n  fill(\"white\");\n  textSize(18);\n  text(\"Score: \" + score, 15, 25);\n  text(\"Health: \" + health, 15, 50);\n}\nfunction showEndScreen(title, subtitle) {\n  background(\"black\");\n  textAlign(CENTER);\n  fill(\"yellow\");\n  textSize(40);\n  text(title, 200, 180);\n  fill(\" white\");\n  textSize(20);\n  text(subtitle, 200, 220);\n  text(\"Final Score: \" + score, 200, 260);\n}\nfunction draw() {\n  handleCollisions();\n  updateBackground();\n  fill(\"white\");\n  textSize(12);\n  text(\"Left and right to move,space to shoot.\", 105, 200);\n  if (enemy.y == 600) {\n    enemy.y = 0;\n  }\n  if (meteor.y == 600) {\n    meteor.y = 0;\n  }\n  if (enemy.isTouching(ship)) {\n      health = health - 1;\n    }\n  if (bullet.isTouching(enemy)) {\n   score = score + 1;\n  bullet.visible = 0;\n  bullet.velocityY = 0;\n  enemy.x = randomNumber(1, 400);\n  enemy.y = 0;\n}\n  if (bullet.isTouching(meteor)) {\n      meteor.x = randomNumber(1, 400);\n      meteor.y = 0;\n      bullet.visible = 0;\n      bullet.velocityY = 0;\n      score = score + 1;\n      bullet.y = ship.y;\n      bullet.x = ship.x;\n    }\n  if (health == 0) {\n      gameState = \"over\";\n    }\n  if (enemy.isTouching(ship)) {\n      enemy.x = randomNumber(1, 400);\n      enemy.y = 0;\n    }\n  if (meteor.isTouching(ship)) {\n      meteor.x = randomNumber(1, 400);\n      meteor.y = 0;\n      health = health - 1;\n    }\n  if (keyWentDown(\"space\") && bullet.visible == 0) {\n      bullet.x = ship.x;\n      bullet.y = ship.y - 45;\n      bullet.visible = 1;\n      bullet.velocityY = -10;\n    }\n  if (bullet.y < 0) {\n      bullet.visible = 0;\n      bullet.velocityY = 0;\n    }\n  if (gameState === \"play\") {\n      handleInput();\n      spawnObstacles();\n      handleCollisions(); \n      drawSprites();\n      displayUI();\n    } else if (gameState === \"win\") {\n      showEndScreen(\"YOU WIN!\", \"The galaxy is safe.\");\n    } else if (gameState === \"over\") {\n      showEndScreen(\"GAME OVER\", \"Try again, pilot.\");\n    }\n  if (bullet.isTouching(enemy)) {\n    enemy.x = randomNumber(1, 400);\nenemy.y = 0;\n    }\n  if (enemy.y >= 400) {\n    enemy.y = 0;\n    health = health - 1;\n  }\n  if (meteor.y >= 400) {\n    meteor.y = 0;\n    health = health - 1;\n  }\n  }\n\n\n\n\n\n\n\n\n\n\n","animations":{"orderedKeys":["8c302c54-4527-4f70-815f-c99b524e2f76","59a3b29d-cfef-4efd-8c76-3a24aa992fd6","b2112a4c-41e4-4887-9040-f0aaab556602","0b39d8be-462e-438b-9902-bef7ac438019"],"propsByKey":{"8c302c54-4527-4f70-815f-c99b524e2f76":{"name":"playerShip1_blue_1","sourceUrl":"/api/v1/animation-library/gamelab/EFY9oqBBpFM5UwPvGD7JcFtTTIiVjD1./category_vehicles/playerShip1_blue.png","frameSize":{"x":99,"y":75},"frameCount":1,"looping":true,"frameDelay":2,"version":"EFY9oqBBpFM5UwPvGD7JcFtTTIiVjD1.","categories":["vehicles"]},"59a3b29d-cfef-4efd-8c76-3a24aa992fd6":{"name":"enemyBlack1_1","sourceUrl":"/api/v1/animation-library/gamelab/0U_SgMD3AShyz1QWKxeGi1T4z3qdtXv6/category_vehicles/enemyBlack1.png","frameSize":{"x":93,"y":84},"frameCount":1,"looping":true,"frameDelay":2,"version":"0U_SgMD3AShyz1QWKxeGi1T4z3qdtXv6","categories":["vehicles"]},"b2112a4c-41e4-4887-9040-f0aaab556602":{"name":"meteor.jpg_1","sourceUrl":null,"frameSize":{"x":225,"y":225},"frameCount":1,"looping":true,"frameDelay":12,"version":"tuvQLWTb725qnqSpC.h1VWncgn1XrvnU","categories":[""]},"0b39d8be-462e-438b-9902-bef7ac438019":{"name":"bullet 2.0.png_1","sourceUrl":null,"frameSize":{"x":225,"y":225},"frameCount":1,"looping":true,"frameDelay":12,"version":"AcrNYgf1x7TtLx4qd.DZ.V9S1YHo0SB1","categories":[""]}}},"inRestrictedShareMode":false,"teacherHasConfirmedUploadWarning":false}